{
    "AX": {
        "error": 0.0071857073990253305,
        "error_type": "SEM",
        "filter_outliers_dict": {
            "filter_outliers": true,
            "iterations": 1,
            "std_devs": 2
        },
        "fit": "Average",
        "fn": 57,
        "include_baseline_error": false,
        "n": 60,
        "reviewed": true,
        "value": -0.12857180082222872
    },
    "CDD": {
        "error": 1.7069776905728683e-05,
        "error_type": "SEM",
        "filter_outliers_dict": {
            "filter_outliers": true,
            "iterations": 1,
            "std_devs": 10
        },
        "fit": "Average",
        "fn": 60,
        "include_baseline_error": false,
        "n": 60,
        "reviewed": true,
        "value": 0.00016478030738653615
    },
    "H1": {
        "error": 0.005137317246956782,
        "error_type": "SEM",
        "filter_outliers_dict": {
            "filter_outliers": true,
            "iterations": 1,
            "std_devs": 2
        },
        "fit": "Average",
        "fn": 55,
        "include_baseline_error": false,
        "n": 60,
        "reviewed": true,
        "value": -0.05123665726066313
    },
    "H2": {
        "error": 0.0028623274738734227,
        "error_type": "SEM",
        "filter_outliers_dict": {
            "filter_outliers": true,
            "iterations": 1,
            "std_devs": 2
        },
        "fit": "Average",
        "fn": 57,
        "include_baseline_error": false,
        "n": 60,
        "reviewed": true,
        "value": -0.07418980521329663
    },
    "L1": {
        "error": 0.0024026686870035974,
        "error_type": "SEM",
        "filter_outliers_dict": {
            "filter_outliers": true,
            "iterations": 1,
            "std_devs": 2
        },
        "fit": "Average",
        "fn": 57,
        "include_baseline_error": false,
        "n": 60,
        "reviewed": true,
        "value": 0.02079972060930327
    },
    "L2": {
        "error": 0.005867322159043242,
        "error_type": "SEM",
        "filter_outliers_dict": {
            "filter_outliers": true,
            "iterations": 1,
            "std_devs": 2
        },
        "fit": "Average",
        "fn": 57,
        "include_baseline_error": false,
        "n": 60,
        "reviewed": true,
        "value": 0.05339523112713339
    }
}